creppl/__init__.py
creppl/__main__.py
creppl/application.py
creppl/cmd/__init__.py
creppl/cmd/on_command.py
creppl/io/__init__.py
creppl/io/fileio.py
creppl/io/terminal.py
creppl/proc/process.py
creppl/ui/prompts.py
creppl/utils/errors.py
creppl/utils/helpers.py
Creppl-1.0.1.dist-info/LICENSE
Creppl-1.0.1.dist-info/METADATA
Creppl-1.0.1.dist-info/WHEEL
Creppl-1.0.1.dist-info/entry_points.txt
Creppl-1.0.1.dist-info/top_level.txt
Creppl-1.0.1.dist-info/RECORD
