Metadata-Version: 2.1
Name: Creppl
Version: 1.0.1
Summary: C++ REPL
Author-email: Joel Thomas <joelthomas.e@gmail.com>
License: GNU GENERAL PUBLIC LICENSE
Project-URL: Homepage, https://github.com/joeletho/creppl
Keywords: c++,repl,python,cpp,cli,terminal
Classifier: Topic :: Text Editors
Classifier: Environment :: Console
Classifier: Operating System :: POSIX :: Linux
Classifier: Programming Language :: Python :: 3.8
Classifier: License :: OSI Approved :: GNU General Public License v3 (GPLv3)
Requires-Python: >=3.8
License-File: LICENSE
Provides-Extra: dev
Requires-Dist: bumpver ; extra == 'dev'
Requires-Dist: pip-tools ; extra == 'dev'
